DataOCREnhanceMain/DataOCREnhance.py
DataOCREnhanceMain/__init__.py
DataOCREnhanceMain-0.0.2.dist-info/LICENSE
DataOCREnhanceMain-0.0.2.dist-info/METADATA
DataOCREnhanceMain-0.0.2.dist-info/WHEEL
DataOCREnhanceMain-0.0.2.dist-info/top_level.txt
DataOCREnhanceMain-0.0.2.dist-info/RECORD
