Metadata-Version: 2.1
Name: DataOCREnhanceMain
Version: 0.0.2
Summary: A toolkit for performing OCR (Optical Character Recognition) tasks
Home-page: https://github.com/iot-Noob/DataOCREnhance
Author: IoT Noob Talha Khalid
Author-email: zjohndavid88@gmail.com
Classifier: Programming Language :: Python :: 3
Classifier: License :: OSI Approved :: MIT License
Classifier: Operating System :: OS Independent
License-File: LICENSE
Requires-Dist: Pillow
Requires-Dist: pytesseract
Requires-Dist: opencv-python
Requires-Dist: numpy
Requires-Dist: nltk
